wj_analysis/common/__init__.py
wj_analysis/common/general_utils.py
wj_analysis/common/metric_transformation.py
wj_analysis/common/nlp_utils.py
wj_analysis/common/stopwords/English.txt
wj_analysis/common/stopwords/Spanish.txt
wj_analysis/common/synchronization.py
wj_analysis/common/tactips.py
wj_analysis/digital_med/P_long_text_pol.py
wj_analysis/digital_med/digital_media.py
wj_analysis/digital_med/g_news.py
wj_analysis/digital_med/long_text_pol.py
wj_analysis/facebook/__init__.py
wj_analysis/facebook/effective_moments.py
wj_analysis/facebook/engagement_rate_sensor.py
wj_analysis/facebook/engagement_rates.py
wj_analysis/facebook/most_effective_content.py
wj_analysis/facebook/polarity_analysis.py
wj_analysis/facebook/polarity_distribution.py
wj_analysis/facebook/social_media_fb.py
wj_analysis/facebook/sttm_groups.py
wj_analysis/facebook/top_polarity_score.py
wj_analysis/facebook/traceability.py
wj_analysis/facebook/word_analysis.py
wj_analysis/facebook_insights/impr_pos_perf.py
wj_analysis/facebook_insights/insights_demographics_kpi.py
wj_analysis/facebook_insights/insights_kpi.py
wj_analysis/facebook_insights/neg_feedback.py
wj_analysis/instagram/__init__.py
wj_analysis/instagram/effective_moments.py
wj_analysis/instagram/engagement_rates.py
wj_analysis/instagram/hashtags.py
wj_analysis/instagram/most_effective_content.py
wj_analysis/instagram/polarity_analysis.py
wj_analysis/instagram/polarity_distribution.py
wj_analysis/instagram/social_media_ig.py
wj_analysis/instagram/sttm_groups.py
wj_analysis/instagram/traceability.py
wj_analysis/reach_fb_ig/reach_fb_ig.py
wj_analysis/twitter/__init__.py
wj_analysis/twitter/effective_moments.py
wj_analysis/twitter/engagement_rates.py
wj_analysis/twitter/most_effective_content.py
wj_analysis/twitter/polarity_analysis.py
wj_analysis/twitter/polarity_distribution.py
wj_analysis/twitter/social_media_tw.py
wj_analysis/twitter/sttm_groups.py
wj_analysis/twitter/top_polarity_score.py
wj_analysis/twitter/traceability.py
wj_analysis-0.8.2.dist-info/LICENSE.md
wj_analysis-0.8.2.dist-info/WHEEL
wj_analysis-0.8.2.dist-info/METADATA
wj_analysis-0.8.2.dist-info/RECORD
