Metadata-Version: 2.1
Name: wj-analysis
Version: 0.8.2
Summary: Whale&Jaguar Libary - Analysis
License: GNU3
Author: Sebastian Franco
Author-email: jsfranco@whaleandjaguar.co
Requires-Python: >3.7.1,<4.0
Classifier: License :: Other/Proprietary License
Classifier: Programming Language :: Python :: 3
Classifier: Programming Language :: Python :: 3.8
Classifier: Programming Language :: Python :: 3.9
Requires-Dist: nltk (>=3.7,<4.0)
Requires-Dist: numpy (==1.21.0)
Requires-Dist: pandas (>=1.3.2,<2.0.0)
Requires-Dist: scikit-learn (>=1.0.2,<2.0.0)
Requires-Dist: spacy (>=3.2.2,<4.0.0)
